audplot/__init__.py
audplot/core/__init__.py
audplot/core/api.py
audplot-1.4.8.dist-info/licenses/LICENSE
docs/changelog.rst
docs/conf.py
docs/contributing.rst
docs/genindex.rst
docs/index.rst
docs/installation.rst
docs/usage.rst
docs/_templates/autosummary/base.rst
docs/_templates/autosummary/class.rst
docs/_templates/autosummary/function.rst
docs/api-src/audplot.rst
tests/test_api.py
audplot-1.4.8.dist-info/METADATA
audplot-1.4.8.dist-info/WHEEL
audplot-1.4.8.dist-info/top_level.txt
audplot-1.4.8.dist-info/RECORD
