Metadata-Version: 2.4
Name: audplot
Version: 1.4.8
Summary: A Python plotting package
Author-email: Johannes Wagner <jwagner@audeering.com>, Hagen Wierstorf <hwierstorf@audeering.com>
License-Expression: MIT
Project-URL: repository, https://github.com/audeering/audplot/
Project-URL: documentation, https://audeering.github.io/audplot/
Keywords: plot,machine learning
Classifier: Development Status :: 5 - Production/Stable
Classifier: Intended Audience :: Science/Research
Classifier: Intended Audience :: Developers
Classifier: Operating System :: OS Independent
Classifier: Programming Language :: Python
Classifier: Programming Language :: Python :: 3
Classifier: Programming Language :: Python :: 3.10
Classifier: Programming Language :: Python :: 3.11
Classifier: Programming Language :: Python :: 3.12
Classifier: Programming Language :: Python :: 3.13
Classifier: Programming Language :: Python :: 3.14
Classifier: Topic :: Scientific/Engineering
Requires-Python: >=3.10
License-File: LICENSE
Requires-Dist: audmath
Requires-Dist: audmetric>=1.1.0
Requires-Dist: matplotlib!=3.6.1
Requires-Dist: seaborn
Dynamic: license-file
